{
"type": "FeatureCollection",
"lastupdate": "2020-07-28T01:29:12Z",
"features": [
	{"geometry":{"coordinates":[-0.817823,52.443918],"type":"Point"},"properties":{"amenity":"recycling","name":"Co-op Supermarket Car Prak","osm_id":"696653753"},"type":"Feature"}
]
}
