{
"type": "FeatureCollection",
"lastupdate": "2020-07-29T00:24:51Z",
"features": [
	{"geometry":{"coordinates":[-2.967282,54.425448],"type":"Point"},"properties":{"amenity":"waste_basket","osm_id":"746858024"},"type":"Feature"},
	{"geometry":{"coordinates":[-2.965871,54.421974],"type":"Point"},"properties":{"amenity":"waste_basket","osm_id":"746858136"},"type":"Feature"},
	{"geometry":{"coordinates":[-2.965265,54.421195],"type":"Point"},"properties":{"amenity":"waste_basket","osm_id":"746858194"},"type":"Feature"},
	{"geometry":{"coordinates":[-2.966891,54.422377],"type":"Point"},"properties":{"amenity":"waste_basket","osm_id":"746858300"},"type":"Feature"},
	{"geometry":{"coordinates":[-2.964235,54.421722],"type":"Point"},"properties":{"amenity":"waste_basket","osm_id":"746858321"},"type":"Feature"},
	{"geometry":{"coordinates":[-2.962575,54.432393],"type":"Point"},"properties":{"amenity":"waste_basket","osm_id":"746858454"},"type":"Feature"},
	{"geometry":{"coordinates":[-2.966044,54.42135],"type":"Point"},"properties":{"amenity":"waste_basket","osm_id":"746858536"},"type":"Feature"},
	{"geometry":{"coordinates":[-2.964599,54.421201],"type":"Point"},"properties":{"amenity":"waste_basket","osm_id":"746858687"},"type":"Feature"},
	{"geometry":{"coordinates":[-2.963259,54.432575],"type":"Point"},"properties":{"amenity":"waste_basket","osm_id":"1359823037"},"type":"Feature"},
	{"geometry":{"coordinates":[-2.970006,54.427468],"type":"Point"},"properties":{"amenity":"recycling","name":"Ambleside Household Waste Recycling Centre","osm_id":"1687642895","tag":{"addr:city":"Ambleside","addr:place":"Rothay Holme","addr:postcode":"LA22 0EE","opening_hours":"08:00-18:00","operator":"Cumbria County Council","recycling:batteries":"yes","recycling:books":"yes","recycling:car_batteries":"yes","recycling:cardboard":"yes","recycling:clothes":"yes","recycling:discs":"yes","recycling:engine_oil":"yes","recycling:fluorescent_tubes":"yes","recycling:fridge_and_freezer":"yes","recycling:garden_waste":"yes","recycling:gas_bottles":"yes","recycling:hardcore":"yes","recycling:household_and_garden_chemicals":"yes","recycling:large_appliances":"yes","recycling:mixed_textiles":"yes","recycling:paint":"yes","recycling:plastic":"yes","recycling:rubble":"yes","recycling:scrap_metal":"yes","recycling:small_appliances":"yes","recycling:tv_monitor":"yes","recycling:wood":"yes","recycling_type":"centre"}},"type":"Feature"},
	{"geometry":{"coordinates":[-2.956442,54.432365],"type":"Point"},"properties":{"amenity":"waste_basket","osm_id":"4173327891"},"type":"Feature"},
	{"geometry":{"coordinates":[-2.963714,54.433601],"type":"Point"},"properties":{"amenity":"waste_basket","osm_id":"4228102617"},"type":"Feature"},
	{"geometry":{"coordinates":[-2.9635,54.431768],"type":"Point"},"properties":{"amenity":"waste_basket","osm_id":"4231573784"},"type":"Feature"},
	{"geometry":{"coordinates":[-2.963762,54.42999],"type":"Point"},"properties":{"amenity":"waste_basket","osm_id":"4231647369"},"type":"Feature"},
	{"geometry":{"coordinates":[-2.962346,54.431046],"type":"Point"},"properties":{"amenity":"waste_basket","osm_id":"4231709277"},"type":"Feature"},
	{"geometry":{"coordinates":[-2.968241,54.428183],"type":"Point"},"properties":{"amenity":"recycling","osm_id":"4232072321"},"type":"Feature"},
	{"geometry":{"coordinates":[-2.966356,54.428091],"type":"Point"},"properties":{"amenity":"waste_basket","osm_id":"4232093611"},"type":"Feature"},
	{"geometry":{"coordinates":[-2.961893,54.419747],"type":"Point"},"properties":{"amenity":"waste_basket","osm_id":"4233624677"},"type":"Feature"},
	{"geometry":{"coordinates":[-2.962337,54.420805],"type":"Point"},"properties":{"amenity":"waste_basket","osm_id":"4233922880"},"type":"Feature"},
	{"geometry":{"coordinates":[-2.964621,54.43005],"type":"Point"},"properties":{"amenity":"waste_basket","osm_id":"5412735125"},"type":"Feature"},
	{"geometry":{"coordinates":[-2.963331,54.429882],"type":"Point"},"properties":{"amenity":"waste_basket","osm_id":"6448285737"},"type":"Feature"},
	{"geometry":{"coordinates":[-2.964368,54.434175],"type":"Point"},"properties":{"amenity":"recycling","osm_id":"6556058958","tag":{"operator":"The Fire Fighters Charity","recycling:clothes":"yes","recycling:handbags":"yes","recycling:linen":"yes","recycling:shoes":"yes","recycling_type":"container"}},"type":"Feature"},
	{"geometry":{"coordinates":[-2.96149,54.425892],"type":"Point"},"properties":{"amenity":"waste_basket","osm_id":"6594677493"},"type":"Feature"},
	{"geometry":{"coordinates":[-2.961671,54.426021],"type":"Point"},"properties":{"amenity":"waste_basket","osm_id":"6594677495"},"type":"Feature"},
	{"geometry":{"coordinates":[-2.9659,54.431056],"type":"Point"},"properties":{"amenity":"waste_basket","osm_id":"7192648198"},"type":"Feature"}
]
}
