{
"type": "FeatureCollection",
"lastupdate": "2020-07-31T01:06:47Z",
"features": [
	{"geometry":{"coordinates":[-2.918851,53.189633],"type":"Point"},"properties":{"amenity":"recycling","name":"Chester Household Waste Recycling Centre","osm_id":"400014300"},"type":"Feature"},
	{"geometry":{"coordinates":[-2.934423,53.173226],"type":"Point"},"properties":{"amenity":"waste_basket","osm_id":"7611719999","tag":{"waste":"dog_excrement"}},"type":"Feature"},
	{"geometry":{"coordinates":[-2.934414,53.173351],"type":"Point"},"properties":{"amenity":"waste_basket","osm_id":"7611720000","tag":{"waste":"trash"}},"type":"Feature"},
	{"geometry":{"coordinates":[-2.936479,53.176836],"type":"Point"},"properties":{"amenity":"waste_basket","osm_id":"7613388099","tag":{"waste":"dog_excrement"}},"type":"Feature"},
	{"geometry":{"coordinates":[-2.933728,53.177162],"type":"Point"},"properties":{"amenity":"waste_basket","osm_id":"7613388100","tag":{"waste":"dog_excrement"}},"type":"Feature"},
	{"geometry":{"coordinates":[-2.932467,53.175721],"type":"Point"},"properties":{"amenity":"waste_basket","osm_id":"7613388101","tag":{"waste":"dog_excrement"}},"type":"Feature"},
	{"geometry":{"coordinates":[-2.93567,53.176782],"type":"Point"},"properties":{"amenity":"waste_basket","osm_id":"7613388102","tag":{"waste":"dog_excrement"}},"type":"Feature"},
	{"geometry":{"coordinates":[-2.930018,53.175714],"type":"Point"},"properties":{"amenity":"waste_basket","osm_id":"7613388103","tag":{"waste":"dog_excrement"}},"type":"Feature"},
	{"geometry":{"coordinates":[-2.928189,53.174664],"type":"Point"},"properties":{"amenity":"waste_basket","osm_id":"7613388104","tag":{"waste":"dog_excrement"}},"type":"Feature"}
]
}
