{
"type": "FeatureCollection",
"lastupdate": "2020-07-24T08:37:10Z",
"features": [
	{"geometry":{"coordinates":[-1.940492,53.604006],"type":"Point"},"properties":{"amenity":"recycling","osm_id":"6002856985","tag":{"location":"overground","recycling_type":"container"}},"type":"Feature"},
	{"geometry":{"coordinates":[-1.954155,53.606421],"type":"Point"},"properties":{"amenity":"waste_basket","osm_id":"6365315189"},"type":"Feature"}
]
}
