{
"type": "FeatureCollection",
"lastupdate": "2020-07-25T00:42:33Z",
"features": [
	{"geometry":{"coordinates":[-2.133219,53.263685],"type":"Point"},"properties":{"amenity":"recycling","osm_id":"248201613"},"type":"Feature"},
	{"geometry":{"coordinates":[-2.127356,53.256956],"type":"Point"},"properties":{"amenity":"recycling","osm_id":"257157567","tag":{"recycling:cans":"yes","recycling:cardboard":"yes","recycling:glass_bottles":"yes","recycling:magazines":"yes","recycling:newspaper":"yes","recycling:paper":"yes","recycling_type":"container"}},"type":"Feature"},
	{"geometry":{"coordinates":[-2.148956,53.240826],"type":"Point"},"properties":{"amenity":"recycling","name":"Macclesfield Refuse Site","osm_id":"319742690","tag":{"recycling:batteries":"yes","recycling:clothes":"yes","recycling:glass":"yes","recycling_type":"centre"}},"type":"Feature"},
	{"geometry":{"coordinates":[-2.121797,53.263465],"type":"Point"},"properties":{"amenity":"recycling","osm_id":"5242262936","tag":{"recycling_type":"centre"}},"type":"Feature"},
	{"geometry":{"coordinates":[-2.169513,53.23135],"type":"Point"},"properties":{"amenity":"waste_basket","osm_id":"6446510103"},"type":"Feature"}
]
}
