{
"type": "FeatureCollection",
"lastupdate": "2020-07-26T00:31:07Z",
"features": [
	{"geometry":{"coordinates":[0.46275,52.224173],"type":"Point"},"properties":{"amenity":"recycling","osm_id":"267132346","tag":{"location":"overground","recycling_type":"container"}},"type":"Feature"},
	{"geometry":{"coordinates":[0.517042,52.245249],"type":"Point"},"properties":{"amenity":"recycling","osm_id":"268811921"},"type":"Feature"},
	{"geometry":{"coordinates":[0.482755,52.252173],"type":"Point"},"properties":{"amenity":"waste_basket","osm_id":"2156722943"},"type":"Feature"}
]
}
