{
"type": "FeatureCollection",
"lastupdate": "2020-07-25T00:42:33Z",
"features": [
	{"geometry":{"coordinates":[-2.013517,50.778372],"type":"Point"},"properties":{"amenity":"waste_basket","osm_id":"1818030083","tag":{"waste":"dog_excrement"}},"type":"Feature"},
	{"geometry":{"coordinates":[-2.003705,50.741757],"type":"Point"},"properties":{"amenity":"recycling","osm_id":"1942736012","tag":{"recycling_type":"container","type":"clothing & shoes"}},"type":"Feature"},
	{"geometry":{"coordinates":[-2.003398,50.746341],"type":"Point"},"properties":{"amenity":"waste_basket","osm_id":"1978076740","tag":{"waste":"dog_excrement"}},"type":"Feature"},
	{"geometry":{"coordinates":[-2.011382,50.74682],"type":"Point"},"properties":{"amenity":"recycling","osm_id":"2262152372"},"type":"Feature"},
	{"geometry":{"coordinates":[-2.00163,50.753891],"type":"Point"},"properties":{"amenity":"waste_basket","osm_id":"2262152693","tag":{"waste":"dog_excrement"}},"type":"Feature"},
	{"geometry":{"coordinates":[-1.996036,50.762318],"type":"Point"},"properties":{"amenity":"waste_basket","osm_id":"2262152777","tag":{"waste":"dog_excrement"}},"type":"Feature"},
	{"geometry":{"coordinates":[-1.958398,50.748626],"type":"Point"},"properties":{"amenity":"waste_basket","name":"Dog waste bin","osm_id":"3177872287"},"type":"Feature"},
	{"geometry":{"coordinates":[-1.968746,50.751562],"type":"Point"},"properties":{"amenity":"recycling","osm_id":"3197075661","tag":{"recycling:clothes":"yes","recycling_type":"container"}},"type":"Feature"},
	{"geometry":{"coordinates":[-1.984493,50.774349],"type":"Point"},"properties":{"amenity":"waste_basket","osm_id":"3198829438"},"type":"Feature"},
	{"geometry":{"coordinates":[-2.017246,50.783714],"type":"Point"},"properties":{"amenity":"waste_basket","osm_id":"4346660721","tag":{"waste":"dog_excrement"}},"type":"Feature"},
	{"geometry":{"coordinates":[-2.016985,50.782691],"type":"Point"},"properties":{"amenity":"waste_basket","osm_id":"4347868505","tag":{"waste":"dog_excrement"}},"type":"Feature"},
	{"geometry":{"coordinates":[-2.01701,50.782717],"type":"Point"},"properties":{"amenity":"waste_basket","osm_id":"4347868506"},"type":"Feature"},
	{"geometry":{"coordinates":[-2.01766,50.779887],"type":"Point"},"properties":{"amenity":"waste_basket","osm_id":"4348405490","tag":{"waste":"dog_excrement"}},"type":"Feature"},
	{"geometry":{"coordinates":[-2.019514,50.781053],"type":"Point"},"properties":{"amenity":"waste_basket","osm_id":"4348405491","tag":{"waste":"dog_excrement"}},"type":"Feature"},
	{"geometry":{"coordinates":[-2.020464,50.781771],"type":"Point"},"properties":{"amenity":"waste_basket","osm_id":"4348405492","tag":{"waste":"dog_excrement"}},"type":"Feature"},
	{"geometry":{"coordinates":[-2.019021,50.782689],"type":"Point"},"properties":{"amenity":"waste_basket","osm_id":"4348405496"},"type":"Feature"},
	{"geometry":{"coordinates":[-2.018993,50.782726],"type":"Point"},"properties":{"amenity":"waste_basket","osm_id":"4348405497","tag":{"waste":"dog_excrement"}},"type":"Feature"},
	{"geometry":{"coordinates":[-2.019881,50.783123],"type":"Point"},"properties":{"amenity":"waste_basket","osm_id":"4348405503","tag":{"waste":"dog_excrement"}},"type":"Feature"},
	{"geometry":{"coordinates":[-2.018105,50.783543],"type":"Point"},"properties":{"amenity":"waste_basket","osm_id":"4348405510","tag":{"waste":"dog_excrement"}},"type":"Feature"},
	{"geometry":{"coordinates":[-2.015207,50.78438],"type":"Point"},"properties":{"amenity":"waste_basket","osm_id":"4348405529","tag":{"waste":"dog_excrement"}},"type":"Feature"},
	{"geometry":{"coordinates":[-2.006089,50.744803],"type":"Point"},"properties":{"amenity":"recycling","osm_id":"6780689716","tag":{"recycling_type":"bin"}},"type":"Feature"},
	{"geometry":{"coordinates":[-2.006099,50.744792],"type":"Point"},"properties":{"amenity":"waste_basket","osm_id":"6780689717"},"type":"Feature"},
	{"geometry":{"coordinates":[-2.005925,50.743952],"type":"Point"},"properties":{"amenity":"waste_basket","osm_id":"6780689718"},"type":"Feature"},
	{"geometry":{"coordinates":[-2.005913,50.743952],"type":"Point"},"properties":{"amenity":"waste_basket","osm_id":"6780689719","tag":{"waste":"dog_excrement"}},"type":"Feature"},
	{"geometry":{"coordinates":[-2.011217,50.746914],"type":"Point"},"properties":{"amenity":"waste_basket","osm_id":"6780689720","tag":{"waste":"trash;dog_excrement"}},"type":"Feature"},
	{"geometry":{"coordinates":[-2.016897,50.755492],"type":"Point"},"properties":{"amenity":"waste_basket","osm_id":"7474296647","tag":{"waste":"dog_excrement"}},"type":"Feature"}
]
}
