{
"type": "FeatureCollection",
"lastupdate": "2020-07-24T00:48:03Z",
"features": [
	{"geometry":{"coordinates":[-1.843235,52.460623],"type":"Point"},"properties":{"amenity":"recycling","name":"Tyseley Public Waste Disposal Site","osm_id":"60028271"},"type":"Feature"},
	{"geometry":{"coordinates":[-1.816183,52.461007],"type":"Point"},"properties":{"amenity":"recycling","osm_id":"463175322"},"type":"Feature"},
	{"geometry":{"coordinates":[-1.821588,52.445978],"type":"Point"},"properties":{"amenity":"recycling","osm_id":"715391576"},"type":"Feature"},
	{"geometry":{"coordinates":[-1.794399,52.464255],"type":"Point"},"properties":{"amenity":"recycling","osm_id":"727768984"},"type":"Feature"},
	{"geometry":{"coordinates":[-1.810213,52.466463],"type":"Point"},"properties":{"amenity":"recycling","osm_id":"762426267"},"type":"Feature"},
	{"geometry":{"coordinates":[-1.80378,52.461218],"type":"Point"},"properties":{"amenity":"recycling","osm_id":"762426353"},"type":"Feature"},
	{"geometry":{"coordinates":[-1.835856,52.438213],"type":"Point"},"properties":{"amenity":"recycling","osm_id":"3778528204"},"type":"Feature"},
	{"geometry":{"coordinates":[-1.785517,52.444582],"type":"Point"},"properties":{"amenity":"recycling","osm_id":"3812374124"},"type":"Feature"},
	{"geometry":{"coordinates":[-1.760893,52.480152],"type":"Point"},"properties":{"amenity":"recycling","osm_id":"4493233290"},"type":"Feature"},
	{"geometry":{"coordinates":[-1.76987,52.441291],"type":"Point"},"properties":{"amenity":"waste_basket","osm_id":"6083698098","tag":{"waste":"dog_excrement"}},"type":"Feature"},
	{"geometry":{"coordinates":[-1.765049,52.442935],"type":"Point"},"properties":{"amenity":"waste_basket","osm_id":"6083698108"},"type":"Feature"},
	{"geometry":{"coordinates":[-1.767497,52.442988],"type":"Point"},"properties":{"amenity":"waste_basket","osm_id":"6083698112"},"type":"Feature"},
	{"geometry":{"coordinates":[-1.767822,52.443563],"type":"Point"},"properties":{"amenity":"waste_basket","osm_id":"6083698120"},"type":"Feature"},
	{"geometry":{"coordinates":[-1.767618,52.441148],"type":"Point"},"properties":{"amenity":"waste_basket","osm_id":"6083698134"},"type":"Feature"},
	{"geometry":{"coordinates":[-1.770257,52.441351],"type":"Point"},"properties":{"amenity":"waste_basket","osm_id":"6083698138"},"type":"Feature"},
	{"geometry":{"coordinates":[-1.770378,52.441896],"type":"Point"},"properties":{"amenity":"waste_basket","osm_id":"6083698139"},"type":"Feature"},
	{"geometry":{"coordinates":[-1.770394,52.442735],"type":"Point"},"properties":{"amenity":"waste_basket","osm_id":"6083698140"},"type":"Feature"},
	{"geometry":{"coordinates":[-1.763315,52.443181],"type":"Point"},"properties":{"amenity":"waste_basket","osm_id":"6083698179"},"type":"Feature"},
	{"geometry":{"coordinates":[-1.763601,52.442775],"type":"Point"},"properties":{"amenity":"waste_basket","osm_id":"6083698180","tag":{"waste":"dog_excrement"}},"type":"Feature"},
	{"geometry":{"coordinates":[-1.763837,52.442863],"type":"Point"},"properties":{"amenity":"waste_basket","osm_id":"6083698181"},"type":"Feature"},
	{"geometry":{"coordinates":[-1.820412,52.438039],"type":"Point"},"properties":{"amenity":"waste_basket","osm_id":"7414632012"},"type":"Feature"},
	{"geometry":{"coordinates":[-1.819815,52.438722],"type":"Point"},"properties":{"amenity":"waste_basket","osm_id":"7414632013"},"type":"Feature"}
]
}
