{
"type": "FeatureCollection",
"lastupdate": "2020-07-28T01:29:12Z",
"features": [
	{"geometry":{"coordinates":[-3.925975,54.942355],"type":"Point"},"properties":{"amenity":"recycling","osm_id":"35706225","tag":{"location":"overground","recycling_type":"container"}},"type":"Feature"},
	{"geometry":{"coordinates":[-3.92372,54.94557],"type":"Point"},"properties":{"amenity":"recycling","osm_id":"5007532063","tag":{"recycling_type":"container"}},"type":"Feature"}
]
}
