{
"type": "FeatureCollection",
"lastupdate": "2020-07-31T01:06:47Z",
"features": [
	{"geometry":{"coordinates":[-1.905172,52.121978],"type":"Point"},"properties":{"amenity":"recycling","osm_id":"3375218944","tag":{"location":"overground","recycling_type":"container"}},"type":"Feature"}
]
}
