{
"type": "FeatureCollection",
"lastupdate": "2020-07-27T00:28:31Z",
"features": [
	{"geometry":{"coordinates":[0.291848,51.449957],"type":"Point"},"properties":{"amenity":"recycling","osm_id":"448524256"},"type":"Feature"},
	{"geometry":{"coordinates":[0.344928,51.431407],"type":"Point"},"properties":{"amenity":"recycling","osm_id":"528921323"},"type":"Feature"},
	{"geometry":{"coordinates":[0.328961,51.426037],"type":"Point"},"properties":{"amenity":"recycling","name":"Pepper Hill Tip","osm_id":"613944595"},"type":"Feature"},
	{"geometry":{"coordinates":[0.3304,51.429589],"type":"Point"},"properties":{"amenity":"recycling","osm_id":"2128986669","tag":{"recycling:glass":"yes"}},"type":"Feature"},
	{"geometry":{"coordinates":[0.275789,51.452],"type":"Point"},"properties":{"amenity":"recycling","osm_id":"3497474475","tag":{"recycling:clothes":"yes","recycling:glass":"yes"}},"type":"Feature"},
	{"geometry":{"coordinates":[0.276521,51.452221],"type":"Point"},"properties":{"amenity":"recycling","osm_id":"3497474476","tag":{"recycling:cans":"no","recycling:clothes":"no","recycling:glass":"no","recycling:paper":"no","recycling:plastic_bags":"yes"}},"type":"Feature"},
	{"geometry":{"coordinates":[0.327143,51.420757],"type":"Point"},"properties":{"amenity":"recycling","name":"Recycling Centre","osm_id":"4315030040"},"type":"Feature"},
	{"geometry":{"coordinates":[0.327148,51.420753],"type":"Point"},"properties":{"amenity":"recycling","osm_id":"4493318730"},"type":"Feature"},
	{"geometry":{"coordinates":[0.320034,51.453637],"type":"Point"},"properties":{"amenity":"waste_basket","osm_id":"6955981534"},"type":"Feature"}
]
}
