{
"type": "FeatureCollection",
"lastupdate": "2020-07-24T00:48:03Z",
"features": [
	{"geometry":{"coordinates":[-1.492826,54.896438],"type":"Point"},"properties":{"amenity":"waste_basket","name":"Dog Waste Bin","osm_id":"3495113395"},"type":"Feature"},
	{"geometry":{"coordinates":[-1.431709,54.917255],"type":"Point"},"properties":{"amenity":"waste_basket","osm_id":"3891422862"},"type":"Feature"},
	{"geometry":{"coordinates":[-1.424518,54.87771],"type":"Point"},"properties":{"amenity":"waste_basket","osm_id":"4032697214"},"type":"Feature"},
	{"geometry":{"coordinates":[-1.424453,54.878101],"type":"Point"},"properties":{"amenity":"waste_basket","osm_id":"4032697215"},"type":"Feature"},
	{"geometry":{"coordinates":[-1.438511,54.879952],"type":"Point"},"properties":{"amenity":"waste_basket","osm_id":"4032766083"},"type":"Feature"},
	{"geometry":{"coordinates":[-1.424432,54.888694],"type":"Point"},"properties":{"amenity":"waste_basket","osm_id":"4033127040"},"type":"Feature"},
	{"geometry":{"coordinates":[-1.425594,54.888744],"type":"Point"},"properties":{"amenity":"waste_basket","osm_id":"4033185677"},"type":"Feature"},
	{"geometry":{"coordinates":[-1.433114,54.893939],"type":"Point"},"properties":{"amenity":"waste_basket","osm_id":"4033246937"},"type":"Feature"},
	{"geometry":{"coordinates":[-1.419117,54.897575],"type":"Point"},"properties":{"amenity":"waste_basket","osm_id":"4034825389"},"type":"Feature"},
	{"geometry":{"coordinates":[-1.450946,54.905319],"type":"Point"},"properties":{"amenity":"waste_basket","osm_id":"4034942302"},"type":"Feature"},
	{"geometry":{"coordinates":[-1.442064,54.899992],"type":"Point"},"properties":{"amenity":"waste_basket","osm_id":"4035035712"},"type":"Feature"},
	{"geometry":{"coordinates":[-1.451002,54.888706],"type":"Point"},"properties":{"amenity":"waste_basket","osm_id":"4045535097"},"type":"Feature"},
	{"geometry":{"coordinates":[-1.446691,54.889029],"type":"Point"},"properties":{"amenity":"waste_basket","osm_id":"4045545339"},"type":"Feature"},
	{"geometry":{"coordinates":[-1.442298,54.886981],"type":"Point"},"properties":{"amenity":"waste_basket","osm_id":"4045555895"},"type":"Feature"},
	{"geometry":{"coordinates":[-1.442619,54.886839],"type":"Point"},"properties":{"amenity":"waste_basket","osm_id":"4045555909"},"type":"Feature"}
]
}
