{
"type": "FeatureCollection",
"lastupdate": "2020-07-29T00:24:51Z",
"features": [
	{"geometry":{"coordinates":[-1.483535,51.797063],"type":"Point"},"properties":{"amenity":"recycling","osm_id":"247176822"},"type":"Feature"},
	{"geometry":{"coordinates":[-1.485124,51.783236],"type":"Point"},"properties":{"amenity":"recycling","osm_id":"1551112098"},"type":"Feature"},
	{"geometry":{"coordinates":[-1.485286,51.78231],"type":"Point"},"properties":{"amenity":"waste_basket","osm_id":"6403106635"},"type":"Feature"},
	{"geometry":{"coordinates":[-1.485244,51.781546],"type":"Point"},"properties":{"amenity":"recycling","osm_id":"6403106637","tag":{"recycling_type":"container"}},"type":"Feature"},
	{"geometry":{"coordinates":[-1.484845,51.7825],"type":"Point"},"properties":{"amenity":"waste_basket","osm_id":"6403106640","tag":{"waste":"dog_excrement"}},"type":"Feature"},
	{"geometry":{"coordinates":[-1.484644,51.7822],"type":"Point"},"properties":{"amenity":"waste_basket","osm_id":"6403106641"},"type":"Feature"},
	{"geometry":{"coordinates":[-1.482974,51.792723],"type":"Point"},"properties":{"amenity":"recycling","name":"T & B Motors","osm_id":"6621257054","tag":{"industrial":"scrap_yard","operator":"T & B Motors","recycling:vehicles":"yes","recycling_type":"scrap_yard","website":"www.vanspares.co.uk/"}},"type":"Feature"},
	{"geometry":{"coordinates":[-1.483613,51.783861],"type":"Point"},"properties":{"amenity":"waste_basket","osm_id":"6757906300"},"type":"Feature"},
	{"geometry":{"coordinates":[-1.482454,51.784083],"type":"Point"},"properties":{"amenity":"waste_basket","osm_id":"6758020379"},"type":"Feature"}
]
}
