{
"type": "FeatureCollection",
"lastupdate": "2020-07-31T01:06:47Z",
"features": [
	{"geometry":{"coordinates":[-1.48351,51.764194],"type":"Point"},"properties":{"amenity":"recycling","osm_id":"250763813"},"type":"Feature"},
	{"geometry":{"coordinates":[-1.410379,51.736992],"type":"Point"},"properties":{"amenity":"recycling","name":"Dix Pit","osm_id":"788436720","tag":{"recycling:batteries":"yes","recycling:cans":"yes","recycling:clothes":"yes","recycling:glass":"yes","recycling:paper":"yes","recycling:scrap_metal":"yes"}},"type":"Feature"},
	{"geometry":{"coordinates":[-1.481933,51.780246],"type":"Point"},"properties":{"amenity":"recycling","osm_id":"796081405","tag":{"recycling:cans":"yes","recycling:clothes":"yes","recycling:glass":"yes","recycling:paper":"yes"}},"type":"Feature"},
	{"geometry":{"coordinates":[-1.487155,51.775514],"type":"Point"},"properties":{"amenity":"waste_basket","osm_id":"6403093698"},"type":"Feature"},
	{"geometry":{"coordinates":[-1.486939,51.775537],"type":"Point"},"properties":{"amenity":"waste_basket","osm_id":"6403093699","tag":{"waste":"dog_excrement"}},"type":"Feature"},
	{"geometry":{"coordinates":[-1.486977,51.774994],"type":"Point"},"properties":{"amenity":"waste_basket","osm_id":"6403098597","tag":{"waste":"dog_excrement"}},"type":"Feature"},
	{"geometry":{"coordinates":[-1.486969,51.774986],"type":"Point"},"properties":{"amenity":"waste_basket","osm_id":"6403098598"},"type":"Feature"},
	{"geometry":{"coordinates":[-1.485023,51.781278],"type":"Point"},"properties":{"amenity":"waste_basket","osm_id":"6403106639"},"type":"Feature"}
]
}
