{
"type": "FeatureCollection",
"lastupdate": "2020-07-30T00:29:16Z",
"features": [
	{"geometry":{"coordinates":[-0.465534,53.723159],"type":"Point"},"properties":{"amenity":"recycling","name":"Humberfield Household Waste Recycling Site","osm_id":"277782640","tag":{"recycling_type":"container"}},"type":"Feature"}
]
}
