{
"type": "FeatureCollection",
"lastupdate": "2020-07-27T00:28:31Z",
"features": [
	{"geometry":{"coordinates":[0.586831,50.854433],"type":"Point"},"properties":{"amenity":"waste_basket","osm_id":"745279400"},"type":"Feature"},
	{"geometry":{"coordinates":[0.537193,50.876742],"type":"Point"},"properties":{"amenity":"recycling","name":"Hasting Tesco recycling","osm_id":"1832070664"},"type":"Feature"},
	{"geometry":{"coordinates":[0.554879,50.850633],"type":"Point"},"properties":{"amenity":"waste_basket","osm_id":"1942528959"},"type":"Feature"},
	{"geometry":{"coordinates":[0.554876,50.85065],"type":"Point"},"properties":{"amenity":"recycling","osm_id":"1942528964"},"type":"Feature"},
	{"geometry":{"coordinates":[0.552869,50.869793],"type":"Point"},"properties":{"amenity":"recycling","osm_id":"6174766307","tag":{"recycling_type":"centre"}},"type":"Feature"}
]
}
