{
"type": "FeatureCollection",
"lastupdate": "2020-07-31T01:06:47Z",
"features": [
	{"geometry":{"coordinates":[-0.341214,51.025421],"type":"Point"},"properties":{"amenity":"recycling","osm_id":"490191025"},"type":"Feature"},
	{"geometry":{"coordinates":[-0.300604,51.022991],"type":"Point"},"properties":{"amenity":"recycling","name":"Recycling Point","osm_id":"3000014316"},"type":"Feature"},
	{"geometry":{"coordinates":[-0.274714,51.051529],"type":"Point"},"properties":{"amenity":"recycling","name":"Recycling Point","osm_id":"3004488106"},"type":"Feature"},
	{"geometry":{"coordinates":[-0.327423,51.060954],"type":"Point"},"properties":{"amenity":"recycling","osm_id":"3071929235","tag":{"recycling_type":"container"}},"type":"Feature"},
	{"geometry":{"coordinates":[-0.335529,51.063301],"type":"Point"},"properties":{"amenity":"recycling","osm_id":"4547769967","tag":{"recycling:batteries":"yes","recycling:clothes":"yes","recycling:small_appliances":"yes","recycling:waste":"yes","recycling_type":"container"}},"type":"Feature"},
	{"geometry":{"coordinates":[-0.35067,51.063226],"type":"Point"},"properties":{"amenity":"waste_basket","osm_id":"4911472445"},"type":"Feature"},
	{"geometry":{"coordinates":[-0.343466,51.059907],"type":"Point"},"properties":{"amenity":"waste_basket","osm_id":"5922249614","tag":{"waste":"dog_excrement"}},"type":"Feature"},
	{"geometry":{"coordinates":[-0.343486,51.059907],"type":"Point"},"properties":{"amenity":"recycling","osm_id":"5922249615","tag":{"location":"overground","recycling:shoes":"yes","recycling_type":"container"}},"type":"Feature"},
	{"geometry":{"coordinates":[-0.321508,51.067095],"type":"Point"},"properties":{"amenity":"recycling","osm_id":"6073646686","tag":{"recycling:shoes":"yes"}},"type":"Feature"},
	{"geometry":{"coordinates":[-0.338929,51.065497],"type":"Point"},"properties":{"amenity":"waste_basket","osm_id":"6289165973","tag":{"waste":"trash"}},"type":"Feature"},
	{"geometry":{"coordinates":[-0.328853,51.062293],"type":"Point"},"properties":{"amenity":"waste_basket","osm_id":"7248585223"},"type":"Feature"},
	{"geometry":{"coordinates":[-0.328429,51.063377],"type":"Point"},"properties":{"amenity":"waste_basket","osm_id":"7248585228"},"type":"Feature"},
	{"geometry":{"coordinates":[-0.328529,51.063241],"type":"Point"},"properties":{"amenity":"waste_basket","osm_id":"7248585230"},"type":"Feature"},
	{"geometry":{"coordinates":[-0.32854,51.063242],"type":"Point"},"properties":{"amenity":"recycling","osm_id":"7248585231","tag":{"recycling_type":"container"}},"type":"Feature"}
]
}
