{
"type": "FeatureCollection",
"lastupdate": "2020-07-28T01:29:12Z",
"features": [
	{"geometry":{"coordinates":[-2.616312,51.19339],"type":"Point"},"properties":{"amenity":"recycling","name":"Hill Quarry Recycling","osm_id":"1449108953","tag":{"recycling:batteries":"yes","recycling:cans":"yes","recycling:cardboard":"yes","recycling:electrical_appliances":"yes","recycling:glass":"yes","recycling:glass_bottles":"yes","recycling:green_waste":"yes","recycling:magazines":"yes","recycling:newspaper":"yes","recycling:paper":"yes","recycling:paper_packaging":"yes","recycling:plastic":"yes","recycling:plastic_bottles":"yes","recycling:small_appliances":"yes","recycling:waste":"yes","recycling_type":"centre"}},"type":"Feature"}
]
}
