{
"type": "FeatureCollection",
"lastupdate": "2020-07-24T00:48:03Z",
"features": [
	{"geometry":{"coordinates":[-1.295648,54.56149],"type":"Point"},"properties":{"amenity":"recycling","name":"Stockton Campus Recycling Centre","osm_id":"413023317"},"type":"Feature"},
	{"geometry":{"coordinates":[-1.28735,54.571899],"type":"Point"},"properties":{"amenity":"recycling","osm_id":"414039168","tag":{"recycling:cans":"yes","recycling:clothes":"yes","recycling:glass":"yes"}},"type":"Feature"},
	{"geometry":{"coordinates":[-1.263196,54.552411],"type":"Point"},"properties":{"amenity":"recycling","osm_id":"740540284"},"type":"Feature"},
	{"geometry":{"coordinates":[-1.316695,54.569416],"type":"Point"},"properties":{"amenity":"recycling","osm_id":"763128459"},"type":"Feature"},
	{"geometry":{"coordinates":[-1.285886,54.544203],"type":"Point"},"properties":{"amenity":"waste_basket","osm_id":"4026238743"},"type":"Feature"},
	{"geometry":{"coordinates":[-1.289629,54.545576],"type":"Point"},"properties":{"amenity":"waste_basket","osm_id":"4034692318"},"type":"Feature"},
	{"geometry":{"coordinates":[-1.307978,54.562596],"type":"Point"},"properties":{"amenity":"waste_basket","osm_id":"4034692321"},"type":"Feature"},
	{"geometry":{"coordinates":[-1.286408,54.546297],"type":"Point"},"properties":{"amenity":"waste_basket","osm_id":"4034692324"},"type":"Feature"},
	{"geometry":{"coordinates":[-1.283978,54.546504],"type":"Point"},"properties":{"amenity":"waste_basket","osm_id":"4034692337"},"type":"Feature"},
	{"geometry":{"coordinates":[-1.303169,54.562251],"type":"Point"},"properties":{"amenity":"waste_basket","osm_id":"4034692415"},"type":"Feature"},
	{"geometry":{"coordinates":[-1.286788,54.547829],"type":"Point"},"properties":{"amenity":"waste_basket","osm_id":"4049955762"},"type":"Feature"},
	{"geometry":{"coordinates":[-1.30397,54.562809],"type":"Point"},"properties":{"amenity":"waste_basket","osm_id":"4106531305"},"type":"Feature"},
	{"geometry":{"coordinates":[-1.2416,54.560434],"type":"Point"},"properties":{"amenity":"recycling","osm_id":"7187507765","tag":{"recycling:cans":"yes","recycling:glass":"yes","recycling:paper":"yes"}},"type":"Feature"},
	{"geometry":{"coordinates":[-1.283492,54.565606],"type":"Point"},"properties":{"amenity":"waste_basket","osm_id":"7669192123"},"type":"Feature"}
]
}
