{
"type": "FeatureCollection",
"lastupdate": "2020-07-28T01:29:12Z",
"features": [
	{"geometry":{"coordinates":[-1.750152,54.713558],"type":"Point"},"properties":{"amenity":"waste_basket","osm_id":"2139394080"},"type":"Feature"},
	{"geometry":{"coordinates":[-1.75066,54.71362],"type":"Point"},"properties":{"amenity":"waste_basket","osm_id":"2139394081"},"type":"Feature"},
	{"geometry":{"coordinates":[-1.749238,54.714713],"type":"Point"},"properties":{"amenity":"waste_basket","osm_id":"2139394083"},"type":"Feature"},
	{"geometry":{"coordinates":[-1.748237,54.717042],"type":"Point"},"properties":{"amenity":"waste_basket","osm_id":"2139394084"},"type":"Feature"},
	{"geometry":{"coordinates":[-1.749308,54.720413],"type":"Point"},"properties":{"amenity":"waste_basket","osm_id":"2139394085"},"type":"Feature"},
	{"geometry":{"coordinates":[-1.75117,54.721791],"type":"Point"},"properties":{"amenity":"waste_basket","osm_id":"2857919986"},"type":"Feature"},
	{"geometry":{"coordinates":[-1.748582,54.717877],"type":"Point"},"properties":{"amenity":"waste_basket","name":"dog bin","osm_id":"2857919987","tag":{"waste":"dog_excrement"}},"type":"Feature"},
	{"geometry":{"coordinates":[-1.754051,54.717755],"type":"Point"},"properties":{"amenity":"waste_basket","osm_id":"2857919988"},"type":"Feature"},
	{"geometry":{"coordinates":[-1.745351,54.714297],"type":"Point"},"properties":{"amenity":"waste_basket","osm_id":"6300971762"},"type":"Feature"},
	{"geometry":{"coordinates":[-1.745335,54.714464],"type":"Point"},"properties":{"amenity":"waste_basket","osm_id":"6300971763"},"type":"Feature"},
	{"geometry":{"coordinates":[-1.745463,54.714437],"type":"Point"},"properties":{"amenity":"waste_basket","osm_id":"6300971764"},"type":"Feature"},
	{"geometry":{"coordinates":[-1.745502,54.714755],"type":"Point"},"properties":{"amenity":"waste_basket","osm_id":"6300971765"},"type":"Feature"},
	{"geometry":{"coordinates":[-1.745313,54.71493],"type":"Point"},"properties":{"amenity":"waste_basket","osm_id":"6301013790"},"type":"Feature"},
	{"geometry":{"coordinates":[-1.74474,54.714852],"type":"Point"},"properties":{"amenity":"waste_basket","osm_id":"6301050288"},"type":"Feature"},
	{"geometry":{"coordinates":[-1.743805,54.715114],"type":"Point"},"properties":{"amenity":"waste_basket","osm_id":"6301090014"},"type":"Feature"},
	{"geometry":{"coordinates":[-1.746348,54.714749],"type":"Point"},"properties":{"amenity":"waste_basket","osm_id":"6304633646"},"type":"Feature"},
	{"geometry":{"coordinates":[-1.746075,54.7148],"type":"Point"},"properties":{"amenity":"waste_basket","osm_id":"6304633647"},"type":"Feature"},
	{"geometry":{"coordinates":[-1.746101,54.714979],"type":"Point"},"properties":{"amenity":"waste_basket","osm_id":"6304641944"},"type":"Feature"},
	{"geometry":{"coordinates":[-1.745432,54.715265],"type":"Point"},"properties":{"amenity":"waste_basket","osm_id":"6304641945"},"type":"Feature"},
	{"geometry":{"coordinates":[-1.745311,54.715312],"type":"Point"},"properties":{"amenity":"waste_basket","osm_id":"6304641946"},"type":"Feature"},
	{"geometry":{"coordinates":[-1.746442,54.713094],"type":"Point"},"properties":{"amenity":"waste_basket","osm_id":"6305250162"},"type":"Feature"},
	{"geometry":{"coordinates":[-1.746564,54.712248],"type":"Point"},"properties":{"amenity":"waste_basket","osm_id":"6305250163"},"type":"Feature"},
	{"geometry":{"coordinates":[-1.753608,54.720758],"type":"Point"},"properties":{"amenity":"waste_basket","osm_id":"6305330495"},"type":"Feature"}
]
}
