{
"type": "FeatureCollection",
"lastupdate": "2020-07-31T01:06:47Z",
"features": [
	{"geometry":{"coordinates":[-1.726191,51.30607],"type":"Point"},"properties":{"amenity":"recycling","name":"Everleigh amenity centre","osm_id":"845343284","tag":{"opening_hours":"Mo-Su 09:00-17:00","recycling:aluminium":"yes","recycling:batteries":"yes","recycling:beverage_cartons":"yes","recycling:cans":"yes","recycling:cardboard":"yes","recycling:cartons":"yes","recycling:chipboard":"yes","recycling:christmas_trees":"yes","recycling:clothes":"yes","recycling:cooking_oil":"yes","recycling:engine_oil":"yes","recycling:flat_glass":"yes","recycling:fluorescent_tubes":"yes","recycling:foil":"yes","recycling:fridge_and_freezer":"yes","recycling:garden_waste":"yes","recycling:glass":"yes","recycling:glass_bottles":"yes","recycling:green_waste":"yes","recycling:light_bulbs":"yes","recycling:low_energy_bulbs":"yes","recycling:magazines":"yes","recycling:mobile_phones":"yes","recycling:newspaper":"yes","recycling:paper":"yes","recycling:paper_packaging":"yes","recycling:plasterboard":"yes","recycling:plastic":"yes","recycling:plastic_bags":"yes","recycling:plastic_bottles":"yes","recycling:printer_cartridges":"yes","recycling:scrap_metal":"yes","recycling:sheet_metal":"yes","recycling:shoes":"yes","recycling:small_appliances":"yes","recycling:tv_monitor":"yes","recycling:tyres":"yes","recycling:waste":"yes"}},"type":"Feature"}
]
}
