{
"type": "FeatureCollection",
"lastupdate": "2020-07-30T00:29:16Z",
"features": [
	{"geometry":{"coordinates":[-3.040222,51.02717],"type":"Point"},"properties":{"amenity":"waste_basket","osm_id":"4124063462","tag":{"waste":"dog_excrement"}},"type":"Feature"},
	{"geometry":{"coordinates":[-3.041704,51.027518],"type":"Point"},"properties":{"amenity":"waste_basket","name":"Dog waste","osm_id":"4490604918","tag":{"waste":"dog_excrement"}},"type":"Feature"},
	{"geometry":{"coordinates":[-3.065972,51.029585],"type":"Point"},"properties":{"amenity":"waste_basket","osm_id":"4668537924","tag":{"waste":"trash"}},"type":"Feature"},
	{"geometry":{"coordinates":[-3.065998,51.029498],"type":"Point"},"properties":{"amenity":"waste_basket","osm_id":"4668537926","tag":{"waste":"dog_excrement"}},"type":"Feature"},
	{"geometry":{"coordinates":[-3.057478,51.035655],"type":"Point"},"properties":{"amenity":"waste_basket","osm_id":"4762613210","tag":{"waste":"trash"}},"type":"Feature"},
	{"geometry":{"coordinates":[-3.041131,51.026563],"type":"Point"},"properties":{"amenity":"waste_basket","osm_id":"4775819795","tag":{"waste":"dog_excrement"}},"type":"Feature"},
	{"geometry":{"coordinates":[-3.062868,51.02224],"type":"Point"},"properties":{"amenity":"waste_basket","osm_id":"4901680620","tag":{"waste":"trash"}},"type":"Feature"},
	{"geometry":{"coordinates":[-3.062836,51.022266],"type":"Point"},"properties":{"amenity":"waste_basket","osm_id":"4901681321","tag":{"waste":"trash"}},"type":"Feature"},
	{"geometry":{"coordinates":[-3.071005,51.033872],"type":"Point"},"properties":{"amenity":"waste_basket","osm_id":"4903917361","tag":{"waste":"dog_excrement"}},"type":"Feature"},
	{"geometry":{"coordinates":[-3.071004,51.033886],"type":"Point"},"properties":{"amenity":"waste_basket","osm_id":"4903917362","tag":{"waste":"trash"}},"type":"Feature"},
	{"geometry":{"coordinates":[-3.063994,51.032139],"type":"Point"},"properties":{"amenity":"waste_basket","osm_id":"4904125290","tag":{"waste":"trash"}},"type":"Feature"},
	{"geometry":{"coordinates":[-3.066974,51.021094],"type":"Point"},"properties":{"amenity":"waste_basket","osm_id":"4925072944","tag":{"waste":"trash"}},"type":"Feature"},
	{"geometry":{"coordinates":[-3.064566,51.021584],"type":"Point"},"properties":{"amenity":"waste_basket","osm_id":"4927179048","tag":{"waste":"trash"}},"type":"Feature"},
	{"geometry":{"coordinates":[-3.064804,51.021594],"type":"Point"},"properties":{"amenity":"waste_basket","osm_id":"4927179049","tag":{"waste":"trash"}},"type":"Feature"},
	{"geometry":{"coordinates":[-3.06186,51.021501],"type":"Point"},"properties":{"amenity":"waste_basket","osm_id":"5186067739","tag":{"waste":"trash"}},"type":"Feature"},
	{"geometry":{"coordinates":[-3.039016,51.027379],"type":"Point"},"properties":{"amenity":"waste_basket","osm_id":"5227788822","tag":{"waste":"trash"}},"type":"Feature"},
	{"geometry":{"coordinates":[-3.048322,51.019567],"type":"Point"},"properties":{"amenity":"waste_basket","osm_id":"5419115543","tag":{"waste":"dog_excrement"}},"type":"Feature"},
	{"geometry":{"coordinates":[-3.072143,51.024236],"type":"Point"},"properties":{"amenity":"waste_basket","osm_id":"5582735614","tag":{"waste":"trash"}},"type":"Feature"},
	{"geometry":{"coordinates":[-3.06478,51.042285],"type":"Point"},"properties":{"amenity":"waste_basket","osm_id":"6834309598","tag":{"waste":"dog_excrement"}},"type":"Feature"}
]
}
