{
"type": "FeatureCollection",
"lastupdate": "2020-07-25T00:42:33Z",
"features": [
	{"geometry":{"coordinates":[-0.556856,51.60824],"type":"Point"},"properties":{"amenity":"recycling","osm_id":"567149976"},"type":"Feature"},
	{"geometry":{"coordinates":[-0.557937,51.610159],"type":"Point"},"properties":{"amenity":"recycling","osm_id":"567149977"},"type":"Feature"},
	{"geometry":{"coordinates":[-0.613344,51.597923],"type":"Point"},"properties":{"amenity":"recycling","name":"Beaconsfield Household Waste and Recycling Centre","osm_id":"715959704","tag":{"operator":"Buckinghamshire County Council","website":"https://www.buckscc.gov.uk/services/waste-and-recycling/locations/beaconsfield/"}},"type":"Feature"},
	{"geometry":{"coordinates":[-0.552713,51.616344],"type":"Point"},"properties":{"amenity":"waste_basket","osm_id":"7040216689"},"type":"Feature"}
]
}
