{
"type": "FeatureCollection",
"lastupdate": "2020-07-25T00:42:33Z",
"features": [
	{"geometry":{"coordinates":[-2.054695,53.413728],"type":"Point"},"properties":{"amenity":"recycling","osm_id":"393722588"},"type":"Feature"},
	{"geometry":{"coordinates":[-2.07804,53.394451],"type":"Point"},"properties":{"amenity":"recycling","name":"Railway Road (Rosehill) Recycling Centre","osm_id":"639185226","tag":{"opening_hours:covid19":"off","operator":"SUEZ","operator:type":"government","recycling_type":"centre"}},"type":"Feature"},
	{"geometry":{"coordinates":[-2.082602,53.414546],"type":"Point"},"properties":{"amenity":"waste_basket","osm_id":"783496553"},"type":"Feature"},
	{"geometry":{"coordinates":[-2.084717,53.414429],"type":"Point"},"properties":{"amenity":"waste_basket","osm_id":"783496648"},"type":"Feature"},
	{"geometry":{"coordinates":[-2.082524,53.414543],"type":"Point"},"properties":{"amenity":"waste_basket","osm_id":"783496650"},"type":"Feature"},
	{"geometry":{"coordinates":[-2.085132,53.414409],"type":"Point"},"properties":{"amenity":"waste_basket","osm_id":"783496652"},"type":"Feature"},
	{"geometry":{"coordinates":[-2.084699,53.414715],"type":"Point"},"properties":{"amenity":"waste_basket","osm_id":"783496656"},"type":"Feature"},
	{"geometry":{"coordinates":[-2.082085,53.415701],"type":"Point"},"properties":{"amenity":"waste_basket","osm_id":"783496669"},"type":"Feature"},
	{"geometry":{"coordinates":[-2.082408,53.415184],"type":"Point"},"properties":{"amenity":"waste_basket","osm_id":"783496671"},"type":"Feature"},
	{"geometry":{"coordinates":[-2.083905,53.414224],"type":"Point"},"properties":{"amenity":"waste_basket","osm_id":"788656101"},"type":"Feature"},
	{"geometry":{"coordinates":[-2.084338,53.414228],"type":"Point"},"properties":{"amenity":"waste_basket","osm_id":"788656160"},"type":"Feature"},
	{"geometry":{"coordinates":[-2.083212,53.414152],"type":"Point"},"properties":{"amenity":"waste_basket","osm_id":"788656212"},"type":"Feature"},
	{"geometry":{"coordinates":[-2.08645,53.413289],"type":"Point"},"properties":{"amenity":"recycling","osm_id":"793803982"},"type":"Feature"},
	{"geometry":{"coordinates":[-2.085926,53.414274],"type":"Point"},"properties":{"amenity":"waste_basket","osm_id":"793804151"},"type":"Feature"},
	{"geometry":{"coordinates":[-2.080292,53.413294],"type":"Point"},"properties":{"amenity":"waste_basket","osm_id":"810792412"},"type":"Feature"},
	{"geometry":{"coordinates":[-2.080197,53.414614],"type":"Point"},"properties":{"amenity":"waste_basket","osm_id":"810792419"},"type":"Feature"},
	{"geometry":{"coordinates":[-2.055213,53.401129],"type":"Point"},"properties":{"amenity":"recycling","osm_id":"1671220394","tag":{"recycling_type":"container"}},"type":"Feature"},
	{"geometry":{"coordinates":[-2.063534,53.394416],"type":"Point"},"properties":{"amenity":"waste_basket","osm_id":"1676720778"},"type":"Feature"},
	{"geometry":{"coordinates":[-2.062292,53.394953],"type":"Point"},"properties":{"amenity":"waste_basket","osm_id":"5271083220"},"type":"Feature"},
	{"geometry":{"coordinates":[-2.061484,53.432331],"type":"Point"},"properties":{"amenity":"waste_basket","osm_id":"7656651676","tag":{"waste":"trash"}},"type":"Feature"}
]
}
