{
"type": "FeatureCollection",
"lastupdate": "2020-07-31T01:06:47Z",
"features": [
	{"geometry":{"coordinates":[-3.254476,56.427042],"type":"Point"},"properties":{"amenity":"recycling","name":"Rait Village Recycling Facility","osm_id":"2178841677","tag":{"recycling_type":"container"}},"type":"Feature"}
]
}
