{
"type": "FeatureCollection",
"lastupdate": "2020-07-30T00:29:16Z",
"features": [
	{"geometry":{"coordinates":[-4.117187,57.592635],"type":"Point"},"properties":{"amenity":"recycling","osm_id":"2420247231","tag":{"recycling:cans":"yes","recycling:clothes":"yes","recycling:glass":"yes","recycling:paper":"yes"}},"type":"Feature"},
	{"geometry":{"coordinates":[-4.112704,57.591823],"type":"Point"},"properties":{"amenity":"recycling","osm_id":"2930080979","tag":{"location":"overground","recycling:cans":"yes","recycling:paper":"yes","recycling_type":"container"}},"type":"Feature"}
]
}
