{
"type": "FeatureCollection",
"lastupdate": "2020-07-31T01:06:47Z",
"features": [
	{"geometry":{"coordinates":[-4.11712,53.23227],"type":"Point"},"properties":{"amenity":"recycling","osm_id":"471185356","tag":{"location":"overground","recycling_type":"container"}},"type":"Feature"},
	{"geometry":{"coordinates":[-4.088577,53.265741],"type":"Point"},"properties":{"amenity":"recycling","osm_id":"2359166625"},"type":"Feature"},
	{"geometry":{"coordinates":[-4.105473,53.254738],"type":"Point"},"properties":{"amenity":"recycling","osm_id":"6118191723","tag":{"recycling:cans":"yes","recycling:clothes":"yes","recycling:glass_bottles":"yes","recycling:plastic_bottles":"yes","recycling_type":"container"}},"type":"Feature"},
	{"geometry":{"coordinates":[-4.122312,53.236672],"type":"Point"},"properties":{"amenity":"waste_basket","osm_id":"7448811607"},"type":"Feature"}
]
}
