{
"type": "FeatureCollection",
"lastupdate": "2020-07-27T00:28:31Z",
"features": [
	{"geometry":{"coordinates":[-0.20578,51.707066],"type":"Point"},"properties":{"amenity":"recycling","name":"Potters Bar Household Waste Recycling Centre","osm_id":"16146555","tag":{"addr:postcode":"EN6 3JN","addr:street":"Cranborne Road","opening_hours":"Mo-Su 08:00-16:00","recycling:aluminium":"yes","recycling:batteries":"yes","recycling:beverage_cartons":"yes","recycling:books":"yes","recycling:cans":"yes","recycling:cardboard":"yes","recycling:cartons":"yes","recycling:chipboard":"yes","recycling:clothes":"yes","recycling:cooking_oil":"yes","recycling:cork":"yes","recycling:engine_oil":"yes","recycling:flat_glass":"yes","recycling:foil":"yes","recycling:fridge_and_freezer":"yes","recycling:garden_waste":"yes","recycling:glass_bottles":"yes","recycling:green_waste":"yes","recycling:magazines":"yes","recycling:newspaper":"yes","recycling:paper":"yes","recycling:paper_packaging":"yes","recycling:plasterboard":"yes","recycling:plastic":"yes","recycling:plastic_bottles":"yes","recycling:polyester":"yes","recycling:scrap_metal":"yes","recycling:sheet_metal":"yes","recycling:shoes":"yes","recycling:small_appliances":"yes","recycling:tv_monitor":"yes","recycling:tyres":"yes","recycling:waste":"yes","recycling:waste_oil":"yes","recycling:white_goods":"yes","recycling:wood":"yes","website":"https://www.hertsmere.gov.uk/environmentplanning/recyclingandwaste/recycling/householdwastedisposalsites.jsp"}},"type":"Feature"},
	{"geometry":{"coordinates":[-0.187799,51.682057],"type":"Point"},"properties":{"amenity":"recycling","name":"Duke of York Garden Centre","osm_id":"1544600871","tag":{"recycling:clothes":"yes","recycling:shoes":"yes"}},"type":"Feature"}
]
}
