{
"type": "FeatureCollection",
"lastupdate": "2020-07-31T01:06:47Z",
"features": [
	{"geometry":{"coordinates":[-3.133271,50.79433],"type":"Point"},"properties":{"amenity":"recycling","name":"Sutton Barton","osm_id":"798060313","tag":{"uri":"http://www.devon.gov.uk/index/environmentplanning/recycling/recycling_centres/sutton_barton_honiton.htm"}},"type":"Feature"}
]
}
