{
"type": "FeatureCollection",
"lastupdate": "2020-07-31T01:06:47Z",
"features": [
	{"geometry":{"coordinates":[-1.320719,52.564872],"type":"Point"},"properties":{"amenity":"recycling","osm_id":"459308934"},"type":"Feature"},
	{"geometry":{"coordinates":[-1.381325,52.553809],"type":"Point"},"properties":{"amenity":"recycling","name":"Morrisons Recycling","osm_id":"3687461843"},"type":"Feature"}
]
}
