{
"type": "FeatureCollection",
"lastupdate": "2020-07-29T00:24:51Z",
"features": [
	{"geometry":{"coordinates":[-4.163723,57.472101],"type":"Point"},"properties":{"amenity":"recycling","osm_id":"391879992"},"type":"Feature"},
	{"geometry":{"coordinates":[-4.14723,57.474347],"type":"Point"},"properties":{"amenity":"waste_basket","osm_id":"458234725","tag":{"waste":"dog_excrement"}},"type":"Feature"},
	{"geometry":{"coordinates":[-4.153554,57.479376],"type":"Point"},"properties":{"amenity":"waste_basket","osm_id":"464778320","tag":{"waste":"dog_excrement"}},"type":"Feature"},
	{"geometry":{"coordinates":[-4.189497,57.46939],"type":"Point"},"properties":{"amenity":"recycling","osm_id":"473495852"},"type":"Feature"},
	{"geometry":{"coordinates":[-4.177921,57.484098],"type":"Point"},"properties":{"amenity":"recycling","osm_id":"5003755820","tag":{"recycling:glass_bottles":"yes","recycling_type":"container"}},"type":"Feature"},
	{"geometry":{"coordinates":[-4.213552,57.478334],"type":"Point"},"properties":{"amenity":"waste_basket","osm_id":"6211479102","tag":{"addr:city":"Inverness","addr:street":"Cawdor Road","waste":"dog_excrement"}},"type":"Feature"},
	{"geometry":{"coordinates":[-4.207085,57.4733],"type":"Point"},"properties":{"amenity":"waste_basket","osm_id":"6211498271","tag":{"addr:city":"Inverness","addr:street":"Diriebught Road"}},"type":"Feature"},
	{"geometry":{"coordinates":[-4.206672,57.476343],"type":"Point"},"properties":{"amenity":"waste_basket","osm_id":"6211498272","tag":{"addr:city":"Inverness","addr:street":"Diriebught Road","waste":"dog_excrement"}},"type":"Feature"}
]
}
