{
"type": "FeatureCollection",
"lastupdate": "2020-07-24T00:48:03Z",
"features": [
	{"geometry":{"coordinates":[-0.677345,52.705051],"type":"Point"},"properties":{"amenity":"recycling","name":"Cottesmore Civic Amenity Site","osm_id":"18384411"},"type":"Feature"}
]
}
