{
"type": "FeatureCollection",
"lastupdate": "2020-07-28T01:29:12Z",
"features": [
	{"geometry":{"coordinates":[0.70933,52.032658],"type":"Point"},"properties":{"amenity":"recycling","name":"Sudbury Household Waste Recycling Centre","osm_id":"309425904","tag":{"recycling:batteries":"yes","recycling:clothes":"yes","recycling:glass":"yes"}},"type":"Feature"},
	{"geometry":{"coordinates":[0.738942,52.037952],"type":"Point"},"properties":{"amenity":"recycling","osm_id":"474737250","tag":{"recycling:glass":"yes"}},"type":"Feature"},
	{"geometry":{"coordinates":[0.734218,52.036209],"type":"Point"},"properties":{"amenity":"recycling","osm_id":"2508817144","tag":{"recycling:cans":"yes","recycling:clothes":"yes","recycling:glass":"yes","recycling:paper":"yes","recycling_type":"container"}},"type":"Feature"},
	{"geometry":{"coordinates":[0.734826,52.036283],"type":"Point"},"properties":{"amenity":"waste_basket","osm_id":"2508817156"},"type":"Feature"},
	{"geometry":{"coordinates":[0.729928,52.038059],"type":"Point"},"properties":{"amenity":"waste_basket","osm_id":"2508817177"},"type":"Feature"},
	{"geometry":{"coordinates":[0.729734,52.038094],"type":"Point"},"properties":{"amenity":"waste_basket","osm_id":"2508817180"},"type":"Feature"}
]
}
