{
"type": "FeatureCollection",
"lastupdate": "2020-07-30T00:29:16Z",
"features": [
	{"geometry":{"coordinates":[-4.276813,55.877318],"type":"Point"},"properties":{"amenity":"recycling","osm_id":"1450561627","tag":{"recycling:cans":"yes","recycling:cardboard":"yes","recycling:cartons":"no","recycling:glass":"no","recycling:glass_bottles":"no","recycling:magazines":"yes","recycling:newspaper":"yes","recycling:paper":"yes","recycling:paper_packaging":"yes","recycling:plastic_bottles":"yes","recycling_type":"container"}},"type":"Feature"},
	{"geometry":{"coordinates":[-4.22992,55.876055],"type":"Point"},"properties":{"amenity":"recycling","osm_id":"1572856726","tag":{"recycling:clothes":"yes","recycling:glass":"yes","recycling:paper":"yes"}},"type":"Feature"},
	{"geometry":{"coordinates":[-4.233383,55.916609],"type":"Point"},"properties":{"amenity":"recycling","osm_id":"1586435287"},"type":"Feature"},
	{"geometry":{"coordinates":[-4.240799,55.878993],"type":"Point"},"properties":{"amenity":"recycling","osm_id":"1776220352","tag":{"recycling:clothes":"yes","recycling:glass":"yes"}},"type":"Feature"},
	{"geometry":{"coordinates":[-4.262798,55.894619],"type":"Point"},"properties":{"amenity":"recycling","osm_id":"2091168657","tag":{"recycling:clothes":"yes","recycling:glass":"yes"}},"type":"Feature"},
	{"geometry":{"coordinates":[-4.239784,55.896641],"type":"Point"},"properties":{"amenity":"recycling","osm_id":"2091264132","tag":{"recycling:glass":"yes"}},"type":"Feature"},
	{"geometry":{"coordinates":[-4.241039,55.896815],"type":"Point"},"properties":{"amenity":"recycling","osm_id":"2091264139","tag":{"recycling:clothes":"yes"}},"type":"Feature"},
	{"geometry":{"coordinates":[-4.288439,55.877296],"type":"Point"},"properties":{"amenity":"recycling","osm_id":"4436703529","tag":{"recycling:glass_bottles":"yes","recycling:plastic_packaging":"yes","recycling_type":"container"}},"type":"Feature"},
	{"geometry":{"coordinates":[-4.28801,55.880488],"type":"Point"},"properties":{"amenity":"recycling","osm_id":"4529094601","tag":{"location":"overground","recycling_type":"container"}},"type":"Feature"},
	{"geometry":{"coordinates":[-4.279044,55.880487],"type":"Point"},"properties":{"amenity":"recycling","osm_id":"4529094604","tag":{"location":"overground","recycling:glass":"yes","recycling_type":"container"}},"type":"Feature"},
	{"geometry":{"coordinates":[-4.28205,55.879846],"type":"Point"},"properties":{"amenity":"recycling","osm_id":"4529094606","tag":{"location":"overground","recycling:cans":"yes","recycling:paper":"yes","recycling:plastic":"yes","recycling_type":"container"}},"type":"Feature"},
	{"geometry":{"coordinates":[-4.281089,55.880548],"type":"Point"},"properties":{"amenity":"recycling","osm_id":"4529094610","tag":{"location":"overground","recycling:cans":"yes","recycling:glass":"yes","recycling:paper":"yes","recycling_type":"container"}},"type":"Feature"},
	{"geometry":{"coordinates":[-4.279261,55.881857],"type":"Point"},"properties":{"amenity":"recycling","osm_id":"4911602568","tag":{"recycling:cans":"yes","recycling:glass":"yes","recycling:paper":"yes","recycling_type":"container"}},"type":"Feature"},
	{"geometry":{"coordinates":[-4.279085,55.881971],"type":"Point"},"properties":{"amenity":"recycling","osm_id":"4911602569","tag":{"recycling:clothes":"yes","recycling_type":"container"}},"type":"Feature"},
	{"geometry":{"coordinates":[-4.27692,55.882506],"type":"Point"},"properties":{"amenity":"recycling","osm_id":"5208035724","tag":{"recycling:cardboard":"yes","recycling:glass":"yes","recycling:paper":"yes","recycling_type":"container"}},"type":"Feature"}
]
}
