{
"type": "FeatureCollection",
"lastupdate": "2020-07-29T00:24:51Z",
"features": [
	{"geometry":{"coordinates":[-4.303126,50.812861],"type":"Point"},"properties":{"amenity":"recycling","osm_id":"2688310371","tag":{"addr:city":"Holsworthy","addr:postcode":"EX22 6NR","addr:street":"Anvil Corner","website":"https://www.devon.gov.uk/index/environment/recycling/recycling_centres/anvil_corner.htm"}},"type":"Feature"}
]
}
